{
    "requestParameters" : {
        "slice" :   10,
        "offset" :  0,
        "length" :  1,
        "orderBy" : "title asc, id desc"
    },
    "uri" :               "%baseURL%folders/%directoryId%/",
    "documents" :         [
        {
            "properties" : {
                "id" :       %test1Id%,
                "title" :    "test 1",
                "icon" :     "api/v1/images/assets/sizes/24x24c/doc.png",
                "initid" :   %test1Initid%,
                "name" :     "TST_APIBASE_TEST_1",
                "revision" : 0
            },
            "uri" :        "%baseURL%documents/%test1Initid%.json"
        }
    ]
}